market_client/__init__.py
market_client/api_client.py
market_client/configuration.py
market_client/rest.py
market_client/api/__init__.py
market_client/api/apps_api.py
market_client/models/__init__.py
market_client/models/app_list_request.py
market_client/models/app_list_response.py
market_client/models/enterprise.py
market_client/models/error_api_response.py
market_client/models/image_info.py
market_client/models/store_app.py
market_client/models/store_app_scope.py
market_client/models/store_app_tag.py
market_client/models/store_app_type.py
market_client/models/store_app_version.py
market_client/models/store_app_version_templete.py
market_client/models/store_app_version_templete_app.py
market_client/models/store_app_version_templete_app_dep_service.py
market_client/models/store_app_version_templete_app_env.py
market_client/models/store_app_version_templete_app_extend_method_rule.py
market_client/models/store_app_version_templete_app_plugin_config.py
market_client/models/store_app_version_templete_app_port.py
market_client/models/store_app_version_templete_app_probe.py
market_client/models/store_app_version_templete_app_share_volume.py
market_client/models/store_app_version_templete_app_volume.py
market_client/models/store_app_version_templete_plugin.py
market_client/models/store_app_version_templete_plugin_config_group.py
market_client/models/store_app_version_templete_plugin_config_group_option.py
test/__init__.py
test/test_app_list_request.py
test/test_app_list_response.py
test/test_apps_api.py
test/test_enterprise.py
test/test_error_api_response.py
test/test_image_info.py
test/test_store_app.py
test/test_store_app_scope.py
test/test_store_app_tag.py
test/test_store_app_type.py
test/test_store_app_version.py
test/test_store_app_version_templete.py
test/test_store_app_version_templete_app.py
test/test_store_app_version_templete_app_dep_service.py
test/test_store_app_version_templete_app_env.py
test/test_store_app_version_templete_app_extend_method_rule.py
rainbond_market_client-0.0.3.dist-info/METADATA
rainbond_market_client-0.0.3.dist-info/WHEEL
rainbond_market_client-0.0.3.dist-info/top_level.txt
rainbond_market_client-0.0.3.dist-info/RECORD
